libjaka-0.1.7.dist-info/METADATA
libjaka-0.1.7.dist-info/WHEEL
libjaka/__init__.py
libjaka/__init__.pyi
libjaka/libjaka.cpython-312-darwin.so
libjaka/py.typed
libjaka-0.1.7.dist-info/RECORD
