Metadata-Version: 2.4
Name: libjaka
Version: 0.1.7
Summary: Rust bindings for the Jaka robot
Keywords: jaka,robot,libjaka
Author: Yixing <yanjizhou312@163.com>
Author-email: Yixing <yanjizhou312@163.com>
License: Apache-2.0
Project-URL: Source Code, https://github.com/Robot-Exp-Platform/libjaka-rs
